ptessentials/__init__.py
ptessentials-0.1.13.dist-info/METADATA
ptessentials-0.1.13.dist-info/WHEEL
ptessentials-0.1.13.dist-info/top_level.txt
ptessentials-0.1.13.dist-info/RECORD
